mkdocs_include_exclude_files/__init__.py
mkdocs_include_exclude_files-0.1.0.dist-info/LICENSE
mkdocs_include_exclude_files-0.1.0.dist-info/METADATA
mkdocs_include_exclude_files-0.1.0.dist-info/WHEEL
mkdocs_include_exclude_files-0.1.0.dist-info/entry_points.txt
mkdocs_include_exclude_files-0.1.0.dist-info/top_level.txt
mkdocs_include_exclude_files-0.1.0.dist-info/RECORD
