Metadata-Version: 2.2
Name: mkdocs_include_exclude_files
Version: 0.1.0
Summary: Modify which files MkDocs includes or excludes.
Home-page: https://github.com/patrick-kidger/mkdocs_include_exclude_files
Author: Patrick Kidger
Author-email: contact@kidger.site
Maintainer: Patrick Kidger
Maintainer-email: contact@kidger.site
License: Apache-2.0
Classifier: Development Status :: 3 - Alpha
Classifier: Intended Audience :: Developers
Classifier: License :: OSI Approved :: Apache Software License
Classifier: Natural Language :: English
Classifier: Programming Language :: Python :: 3
Requires-Python: ~=3.8
License-File: LICENSE
Requires-Dist: mkdocs>=1.2.3
Dynamic: author
Dynamic: author-email
Dynamic: classifier
Dynamic: description
Dynamic: description-content-type
Dynamic: home-page
Dynamic: license
Dynamic: maintainer
Dynamic: maintainer-email
Dynamic: requires-dist
Dynamic: requires-python
Dynamic: summary
